CHANGES.txt
COPYRIGHT.txt
LICENSE.txt
README.txt
bootstrap.py
buildout.cfg
setup.py
src/z3c/__init__.py
src/z3c.profiler.egg-info/PKG-INFO
src/z3c.profiler.egg-info/SOURCES.txt
src/z3c.profiler.egg-info/dependency_links.txt
src/z3c.profiler.egg-info/namespace_packages.txt
src/z3c.profiler.egg-info/not-zip-safe
src/z3c.profiler.egg-info/requires.txt
src/z3c.profiler.egg-info/top_level.txt
src/z3c/profiler/README.txt
src/z3c/profiler/TODO.txt
src/z3c/profiler/__init__.py
src/z3c/profiler/configure.zcml
src/z3c/profiler/ftesting.zcml
src/z3c/profiler/interfaces.py
src/z3c/profiler/layer.py
src/z3c/profiler/setup.zcml
src/z3c/profiler/skin.py
src/z3c/profiler/testing.py
src/z3c/profiler/tests.py
src/z3c/profiler/wsgi.py
src/z3c/profiler/browser/README.txt
src/z3c/profiler/browser/__init__.py
src/z3c/profiler/browser/configure.zcml
src/z3c/profiler/browser/favicon.png
src/z3c/profiler/browser/help.pt
src/z3c/profiler/browser/help.py
src/z3c/profiler/browser/menu.pt
src/z3c/profiler/browser/menu.py
src/z3c/profiler/browser/profiler.css
src/z3c/profiler/browser/profiler.pt
src/z3c/profiler/browser/profiler.py
src/z3c/profiler/browser/template.pt
src/z3c/profiler/browser/img/buttonBG.gif
src/z3c/profiler/browser/img/logo.gif
src/z3c/profiler/browser/img/logo.png
src/z3c/profiler/browser/img/menuBG.jpg
src/z3c/profiler/browser/img/menuSeparator.gif
src/z3c/profiler/browser/img/topBG.gif